journal_club/__init__.py
journal_club/__version__.py
journal_club/countdown.wav
journal_club/jc.py
journal_club/jc_algorithm.py
journal_club/sound.py
journal_club/test2.py
journal_club-0.3.0.dist-info/DESCRIPTION.rst
journal_club-0.3.0.dist-info/METADATA
journal_club-0.3.0.dist-info/RECORD
journal_club-0.3.0.dist-info/WHEEL
journal_club-0.3.0.dist-info/entry_points.txt
journal_club-0.3.0.dist-info/metadata.json
journal_club-0.3.0.dist-info/top_level.txt
