Metadata-Version: 2.0
Name: journal-club
Version: 0.3.0
Summary: Weighted scheme to choose a person to present in a Journal Club
Home-page: https://github.com/philastrophist/journal_club
Author: philastrophist
Author-email: shaun.c.read@gmail.com
License: MIT
Platform: UNKNOWN
Classifier: License :: OSI Approved :: MIT License
Classifier: Programming Language :: Python
Classifier: Programming Language :: Python :: 2.6
Classifier: Programming Language :: Python :: 2.7
Classifier: Programming Language :: Python :: 3
Classifier: Programming Language :: Python :: 3.3
Classifier: Programming Language :: Python :: 3.4
Classifier: Programming Language :: Python :: 3.5
Classifier: Programming Language :: Python :: 3.6
Classifier: Programming Language :: Python :: Implementation :: CPython
Classifier: Programming Language :: Python :: Implementation :: PyPy
Requires-Dist: gtts
Requires-Dist: numpy
Requires-Dist: pandas
Requires-Dist: pydub
Requires-Dist: pyglet
